nvcl_kit-1.2.10.dist-info/METADATA
nvcl_kit-1.2.10.dist-info/WHEEL
nvcl_kit-1.2.10.dist-info/entry_points.txt
nvcl_kit-1.2.10.dist-info/licenses/LICENSE
nvcl_kit/__init__.py
nvcl_kit/constants.py
nvcl_kit/cql_filter.py
nvcl_kit/generators.py
nvcl_kit/param_builder.py
nvcl_kit/reader.py
nvcl_kit/svc_interface.py
nvcl_kit/wfs_helpers.py
nvcl_kit/xml_filter.py
nvcl_kit/xml_helpers.py
nvcl_kit-1.2.10.dist-info/RECORD
