Metadata-Version: 2.1
Name: nvcl_kit
Version: 1.2.10
Summary: Downloads Australian National Virtual Core Library (NVCL) datasets
Author-Email: Vincent Fazio <vincent.fazio@csiro.au>
License: CSIRO BSD/MIT
Classifier: Development Status :: 5 - Production/Stable
Classifier: Intended Audience :: Developers
Classifier: License :: OSI Approved :: BSD License
Classifier: Operating System :: POSIX :: Linux
Classifier: Programming Language :: Python :: 3
Classifier: Programming Language :: Python :: 3.9
Classifier: Programming Language :: Python :: 3.10
Classifier: Programming Language :: Python :: 3.11
Classifier: Programming Language :: Python :: 3.12
Classifier: Topic :: Scientific/Engineering
Project-URL: Homepage, https://github.com/AuScope/nvcl_kit
Requires-Python: >=3.9
Requires-Dist: shapely>=2.0.4
Requires-Dist: requests>=2.31.0
Requires-Dist: pyyaml>=6.0.1
Requires-Dist: pyproj>=3.5.0
Requires-Dist: python-dateutil>=2.9.0.post0
